met_office_datasets/__init__.py
met_office_datasets/_version.py
met_office_datasets/air_quality_cat.yaml
met_office_datasets/mogreps_uk_cat.yaml
met_office_datasets/cats/air_quality_cat.yaml
met_office_datasets/cats/mogreps_uk_cat.yaml
met_office_datasets/cats/ukv_timeseries.yaml
met_office_datasets/cats/mogreps_uk/depth_level_data.yaml
met_office_datasets/cats/mogreps_uk/height_level_data.yaml
met_office_datasets/cats/mogreps_uk/pressure_level_data.yaml
met_office_datasets/cats/mogreps_uk/single_level_data.yaml
met_office_datasets/datasources/__init__.py
met_office_datasets/datasources/aq_datasource.py
met_office_datasets/datasources/dataset.py
met_office_datasets/datasources/historic.py
met_office_datasets/datasources/utils.py
met_office_datasets/zarrhypothetic/__init__.py
met_office_datasets/zarrhypothetic/zarrhypothetic.py
met_office_datasets-0.0.17.dist-info/LICENSE
met_office_datasets-0.0.17.dist-info/METADATA
met_office_datasets-0.0.17.dist-info/WHEEL
met_office_datasets-0.0.17.dist-info/entry_points.txt
met_office_datasets-0.0.17.dist-info/top_level.txt
met_office_datasets-0.0.17.dist-info/zip-safe
met_office_datasets-0.0.17.dist-info/RECORD
